pipask/__init__.py
pipask/_vendor/__init__.py
pipask/_vendor/pip/AUTHORS.txt
pipask/_vendor/pip/LICENSE.txt
pipask/_vendor/pip/README.rst
pipask/_vendor/pip/SECURITY.md
pipask/_vendor/pip/__init__.py
pipask/_vendor/pip/_internal/__init__.py
pipask/_vendor/pip/_internal/build_env.py
pipask/_vendor/pip/_internal/cache.py
pipask/_vendor/pip/_internal/cli/__init__.py
pipask/_vendor/pip/_internal/cli/base_command.py
pipask/_vendor/pip/_internal/cli/cmdoptions.py
pipask/_vendor/pip/_internal/cli/command_context.py
pipask/_vendor/pip/_internal/cli/main_parser.py
pipask/_vendor/pip/_internal/cli/parser.py
pipask/_vendor/pip/_internal/cli/progress_bars.py
pipask/_vendor/pip/_internal/cli/req_command.py
pipask/_vendor/pip/_internal/cli/spinners.py
pipask/_vendor/pip/_internal/cli/status_codes.py
pipask/_vendor/pip/_internal/commands/__init__.py
pipask/_vendor/pip/_internal/commands/install.py
pipask/_vendor/pip/_internal/configuration.py
pipask/_vendor/pip/_internal/distributions/__init__.py
pipask/_vendor/pip/_internal/distributions/base.py
pipask/_vendor/pip/_internal/distributions/installed.py
pipask/_vendor/pip/_internal/distributions/sdist.py
pipask/_vendor/pip/_internal/distributions/wheel.py
pipask/_vendor/pip/_internal/exceptions.py
pipask/_vendor/pip/_internal/index/__init__.py
pipask/_vendor/pip/_internal/index/collector.py
pipask/_vendor/pip/_internal/index/package_finder.py
pipask/_vendor/pip/_internal/index/sources.py
pipask/_vendor/pip/_internal/locations/__init__.py
pipask/_vendor/pip/_internal/locations/_distutils.py
pipask/_vendor/pip/_internal/locations/_sysconfig.py
pipask/_vendor/pip/_internal/locations/base.py
pipask/_vendor/pip/_internal/metadata/__init__.py
pipask/_vendor/pip/_internal/metadata/_json.py
pipask/_vendor/pip/_internal/metadata/base.py
pipask/_vendor/pip/_internal/metadata/importlib/__init__.py
pipask/_vendor/pip/_internal/metadata/importlib/_compat.py
pipask/_vendor/pip/_internal/metadata/importlib/_dists.py
pipask-0.9.7.dist-info/LICENSE
pipask-0.9.7.dist-info/METADATA
pipask-0.9.7.dist-info/WHEEL
pipask-0.9.7.dist-info/entry_points.txt
pipask-0.9.7.dist-info/RECORD
