Metadata-Version: 2.3
Name: pipask
Version: 0.9.7
Summary: Safer python package installation with audit and consent before install
License: MIT
Keywords: pip,security
Author: Feynmanix
Author-email: feynmanix@users.noreply.github.com
Requires-Python: >=3.10
Classifier: License :: OSI Approved :: MIT License
Classifier: Intended Audience :: Developers
Classifier: Environment :: Console
Classifier: Topic :: Software Development
Classifier: Programming Language :: Python :: 3
Classifier: Programming Language :: Python :: 3.10
Classifier: Programming Language :: Python :: 3.11
Classifier: Programming Language :: Python :: 3.12
Requires-Dist: cachecontrol (>=0.14.2,<0.15.0)
Requires-Dist: cvss (>=3.4,<4.0)
Requires-Dist: distro (>=1.9.0,<2.0.0)
Requires-Dist: httpx (>=0.28.1,<0.29.0)
Requires-Dist: packaging (>=21.3,<22.0)
Requires-Dist: platformdirs (>=3.8.1,<4.0.0)
Requires-Dist: pydantic (>=2.10.6,<3.0.0)
Requires-Dist: pyproject-hooks (>=1.2.0,<2.0.0)
Requires-Dist: requests (>=2.32.3,<3.0.0)
Requires-Dist: resolvelib (>=1.1.0,<2.0.0)
Requires-Dist: rich (>=13.9.4,<14.0.0)
Requires-Dist: tenacity (>=9.1.2,<10.0.0)
Requires-Dist: tomli (>=2.2.1,<3.0.0)
Requires-Dist: truststore (>=0.10.1,<0.11.0)
Requires-Dist: urllib3 (>=1.26.17,<2.0.0)
Project-URL: Documentation, https://github.com/feynmanix/pipask/blob/main/README.md
Project-URL: Repository, https://github.com/feynmanix/pipask
